odoo/addons/partner_fax/README.rst
odoo/addons/partner_fax/__init__.py
odoo/addons/partner_fax/__manifest__.py
odoo/addons/partner_fax/i18n/ca.po
odoo/addons/partner_fax/i18n/ca_ES.po
odoo/addons/partner_fax/i18n/de.po
odoo/addons/partner_fax/i18n/es.po
odoo/addons/partner_fax/i18n/fr.po
odoo/addons/partner_fax/i18n/hr_HR.po
odoo/addons/partner_fax/i18n/it.po
odoo/addons/partner_fax/i18n/nl.po
odoo/addons/partner_fax/i18n/partner_fax.pot
odoo/addons/partner_fax/i18n/sl.po
odoo/addons/partner_fax/models/__init__.py
odoo/addons/partner_fax/models/res_partner.py
odoo/addons/partner_fax/static/description/icon.png
odoo/addons/partner_fax/static/description/index.html
odoo/addons/partner_fax/views/res_partner.xml
odoo12_addon_partner_fax-12.0.1.1.1.dist-info/METADATA
odoo12_addon_partner_fax-12.0.1.1.1.dist-info/WHEEL
odoo12_addon_partner_fax-12.0.1.1.1.dist-info/top_level.txt
odoo12_addon_partner_fax-12.0.1.1.1.dist-info/RECORD
